LICENSE
MANIFEST.in
README.md
setup.py
test.py
WebTools.egg-info/PKG-INFO
WebTools.egg-info/SOURCES.txt
WebTools.egg-info/dependency_links.txt
WebTools.egg-info/requires.txt
WebTools.egg-info/top_level.txt
docs/Makefile
docs/conf.py
docs/index.rst
docs/make.bat
docs/_build/doctrees/environment.pickle
docs/_build/doctrees/index.doctree
docs/_build/doctrees/modules/handlers.doctree
docs/_build/doctrees/modules/helpers.doctree
docs/_build/doctrees/modules/index.doctree
docs/_build/doctrees/modules/request.doctree
docs/_build/doctrees/modules/response.doctree
docs/_build/doctrees/modules/route.doctree
docs/_build/doctrees/modules/wsgi.doctree
docs/_build/html/.buildinfo
docs/_build/html/genindex.html
docs/_build/html/index.html
docs/_build/html/objects.inv
docs/_build/html/py-modindex.html
docs/_build/html/search.html
docs/_build/html/searchindex.js
docs/_build/html/_sources/index.txt
docs/_build/html/_sources/modules/handlers.txt
docs/_build/html/_sources/modules/helpers.txt
docs/_build/html/_sources/modules/index.txt
docs/_build/html/_sources/modules/request.txt
docs/_build/html/_sources/modules/response.txt
docs/_build/html/_sources/modules/route.txt
docs/_build/html/_sources/modules/wsgi.txt
docs/_build/html/_static/ajax-loader.gif
docs/_build/html/_static/basic.css
docs/_build/html/_static/comment-bright.png
docs/_build/html/_static/comment-close.png
docs/_build/html/_static/comment.png
docs/_build/html/_static/default.css
docs/_build/html/_static/doctools.js
docs/_build/html/_static/down-pressed.png
docs/_build/html/_static/down.png
docs/_build/html/_static/file.png
docs/_build/html/_static/jquery.js
docs/_build/html/_static/minus.png
docs/_build/html/_static/plus.png
docs/_build/html/_static/pygments.css
docs/_build/html/_static/searchtools.js
docs/_build/html/_static/sidebar.js
docs/_build/html/_static/underscore.js
docs/_build/html/_static/up-pressed.png
docs/_build/html/_static/up.png
docs/_build/html/_static/websupport.js
docs/_build/html/modules/handlers.html
docs/_build/html/modules/helpers.html
docs/_build/html/modules/index.html
docs/_build/html/modules/request.html
docs/_build/html/modules/response.html
