Metadata-Version: 1.0
Name: WebTools
Version: 1.0.2
Summary: Web application development framework
Home-page: https://github.com/bourqujl/webtools
Author: UNKNOWN
Author-email: UNKNOWN
License: UNKNOWN
Platform: UNKNOWN
